g3po/__init__.py
g3po/helper.py
g3po/ldap_to_gen3.py
g3po/main.py
tests/__init__.py
tests/test_main.py
g3po-0.5.1.dist-info/LICENSE
g3po-0.5.1.dist-info/METADATA
g3po-0.5.1.dist-info/WHEEL
g3po-0.5.1.dist-info/entry_points.txt
g3po-0.5.1.dist-info/top_level.txt
g3po-0.5.1.dist-info/RECORD
