Metadata-Version: 2.1
Name: g3po
Version: 0.5.1
Summary: Assorted utility CLI to work with Gen3
Home-page: https://github.com/umccr/g3po
Author: UMCCR
Author-email: services@umccr.org
License: MIT
Platform: UNKNOWN
Requires-Python: >=3.6,<=3.8
Requires-Dist: click (<8.0.0)
Requires-Dist: gen3 (>=4.2.0)
Requires-Dist: indexclient (>=2.1)
Requires-Dist: dictionaryutils (>=3.4.2)
Requires-Dist: gen3users (>=0.7.0)
Requires-Dist: ldap3 (>=2.9.1)
Requires-Dist: importlib-metadata (<2.0.0)
Requires-Dist: yglu (>=1.1.1)
Requires-Dist: jsonschema (==2.5.1)
Requires-Dist: setuptools
Requires-Dist: setuptools-scm
Requires-Dist: wheel
Provides-Extra: dev
Requires-Dist: twine ; extra == 'dev'
Requires-Dist: setuptools ; extra == 'dev'
Requires-Dist: wheel ; extra == 'dev'
Provides-Extra: test
Requires-Dist: pytest ; extra == 'test'
